barbell2_castor/__init__.py
barbell2_castor/api.py
barbell2_castor/castor2sqlite.py
barbell2_castor/query.py
barbell2_castor/utils.py
barbell2_castor-0.8.0.dist-info/METADATA
barbell2_castor-0.8.0.dist-info/WHEEL
barbell2_castor-0.8.0.dist-info/entry_points.txt
barbell2_castor-0.8.0.dist-info/top_level.txt
barbell2_castor-0.8.0.dist-info/RECORD
