Metadata-Version: 2.1
Name: barbell2-castor
Version: 0.8.0
Summary: Utilities for interfacing with Castor EDC
Home-page: https://github.com/rbrecheisen/barbell2_castor
Author: Ralph Brecheisen
Author-email: r.brecheisen@maastrichtuniversity.nl
License: MIT license
Keywords: barbell2_castor
Platform: UNKNOWN
Classifier: Development Status :: 2 - Pre-Alpha
Classifier: Intended Audience :: Developers
Classifier: License :: OSI Approved :: MIT License
Classifier: Natural Language :: English
Classifier: Programming Language :: Python :: 3
Classifier: Programming Language :: Python :: 3.5
Classifier: Programming Language :: Python :: 3.6
Classifier: Programming Language :: Python :: 3.7
Classifier: Programming Language :: Python :: 3.8
Requires-Python: >=3.5
Requires-Dist: oauthlib
Requires-Dist: requests-oauthlib
Requires-Dist: pandas
